[
  {
    "id": "allow-anonymous-with-header-admin",
    "version": "v0.40.3",
    "upstream": {
      "preserve_host": true,
      "url": "http://kratos-selfservice-ui-kratos-selfservice-ui-node.selfservice-ui-namespace.svc.cluster.local:80/auth/"
    },
    "match": {
      "url": "<https|http>://demo.neighbook.tech/ory/<.*>",
      "methods": [
        "GET"
      ]
    },
    "authenticators": [
      {
        "handler": "cookie_session"
      }
    ],
    "authorizer": {
      "handler": "allow"
    },
    "mutators": [
      {
        "handler": "noop"
      }
    ],
    "error": {
      "handler": "redirect",
      "config": {
        "to": "https://demo.neighbook.tech/auth/login"
      }
    }
  }
]